rubix/__init__.py
rubix/kubernetes.py
rubix/utils.py
rubix/assets/__init__.py
rubix/assets/css/__init__.py
rubix/assets/css/custom.css
rubix/aws/__init__.py
rubix/aws/base.py
rubix/aws/cloudwatch.py
rubix/aws/ecs.py
rubix-0.0.9.dist-info/METADATA
rubix-0.0.9.dist-info/RECORD
rubix-0.0.9.dist-info/WHEEL
rubix-0.0.9.dist-info/top_level.txt
