Metadata-Version: 2.1
Name: rubix
Version: 0.0.9
Summary: Python package to enables DevOps tasks in Jupyter Notebooks
Home-page: UNKNOWN
Author: Amit Rathi
Author-email: UNKNOWN
License: GNU Lesser General Public License v3.0
Keywords: DevOps,Jupyter,nurtch
Platform: UNKNOWN
Requires-Dist: wheel
Requires-Dist: plotly
Requires-Dist: pandas
Requires-Dist: boto3
Requires-Dist: kubernetes
Requires-Dist: ipywidgets
Requires-Dist: ipython-sql
Requires-Dist: psycopg2-binary
